boldi/_webalbum_app_version.py
boldi/webalbum/app/__init__.py
boldi/webalbum/app/asgi.py
boldi/webalbum/app/cli.py
boldi/webalbum/app/settings.py
boldi/webalbum/app/urls.py
boldi/webalbum/app/wsgi.py
boldi_webalbum_app-0.9.7.dist-info/METADATA
boldi_webalbum_app-0.9.7.dist-info/WHEEL
boldi_webalbum_app-0.9.7.dist-info/entry_points.txt
boldi_webalbum_app-0.9.7.dist-info/RECORD
