Metadata-Version: 2.4
Name: boldi-webalbum-app
Version: 0.9.7
Summary: boldi.webalbum.app part of Boldi's Python libraries
Author-email: Boldizsár Palotás <boldizsar.palotas@gmail.com>
License: MIT
Requires-Python: >=3.12
Requires-Dist: django>=5.1
Provides-Extra: dev
Requires-Dist: django-stubs; extra == 'dev'
